tempo_pypack/LoopTimer.py
tempo_pypack/__init__.py
tempo_pypack/timer.py
tempo_pypack-0.1.1.dist-info/LICENCE
tempo_pypack-0.1.1.dist-info/METADATA
tempo_pypack-0.1.1.dist-info/WHEEL
tempo_pypack-0.1.1.dist-info/RECORD
