Metadata-Version: 2.3
Name: tempo-pypack
Version: 0.1.1
Summary: Python library for tracking runtime and monitoring loop progress.
License: MIT
Author: Henrique Reis 
Author-email: henrique.hrf@outlook.com
Requires-Python: >=3.12
Classifier: License :: OSI Approved :: MIT License
Classifier: Programming Language :: Python :: 3
Classifier: Programming Language :: Python :: 3.12
Classifier: Programming Language :: Python :: 3.13
